{
    "fields": [
        {
            "key": "name",
            "label": "Nombre del Rol",
            "type": "text",
            "placeholder": "Ej. Tech Lead",
            "rules": ["required", "min:3"]
        },
        {
            "key": "description",
            "label": "Descripción",
            "type": "textarea",
            "placeholder": "Misión o responsabilidades del rol",
            "rules": ["required"]
        },
        {
            "key": "agent_id",
            "label": "AI Agent Principal",
            "type": "select",
            "catalog": "agents",
            "placeholder": "Seleccione el Agente Orquestador"
        },
        {
            "key": "blueprint_id",
            "label": "Plantilla Base",
            "type": "select",
            "catalog": "blueprints",
            "placeholder": "Seleccione el Blueprint o Plantilla Arquitectónica"
        }
    ],
    "catalogs": ["agents", "blueprints"]
}
